CNNreg/__init__.py
CNNreg/cli.py
CNNreg/data.py
CNNreg/layers.py
CNNreg/losses.py
CNNreg/train.py
cnnreg-0.1.0.dist-info/licenses/LICENSE
cnnreg-0.1.0.dist-info/METADATA
cnnreg-0.1.0.dist-info/WHEEL
cnnreg-0.1.0.dist-info/entry_points.txt
cnnreg-0.1.0.dist-info/top_level.txt
cnnreg-0.1.0.dist-info/RECORD
