Metadata-Version: 2.4
Name: CNNreg
Version: 0.1.0
Summary: CNN-based regression for cell type deconvolution of bulk RNA-seq using scRNA-seq reference
Author-email: Xue Wang <wang.xue@mayo.edu>
Maintainer-email: Yuanhang Liu <liu.yuanhang@mayo.edu>, Xue Wang <wang.xue@mayo.edu>
License: MIT
Requires-Python: >=3.9
License-File: LICENSE
Requires-Dist: torch>=1.10.0
Requires-Dist: torchmetrics>=0.10.0
Requires-Dist: torchsort>=0.1.0
Requires-Dist: numpy
Requires-Dist: pandas
Dynamic: license-file
